README.md
setup.cfg
setup.py
reverse_int/__init__.py
reverse_int.egg-info/PKG-INFO
reverse_int.egg-info/SOURCES.txt
reverse_int.egg-info/dependency_links.txt
reverse_int.egg-info/not-zip-safe
reverse_int.egg-info/top_level.txt