Metadata-Version: 1.1
Name: reverse-int
Version: 0.1
Summary: A Simpler lib to Reverse integer
Home-page: https://github.com/Arinze1020/reverse_int.git
Author: Ugwuanyi Arinze
Author-email: arinzeugwuanyi@gmail.com
License: MIT
Platform: UNKNOWN
Classifier: Development Status :: 4 - Beta
Classifier: Intended Audience :: Developers
Classifier: Topic :: Software Development :: Build Tools
Classifier: License :: OSI Approved :: MIT License
Classifier: Programming Language :: Python :: 3
Classifier: Programming Language :: Python :: 3.4
Classifier: Programming Language :: Python :: 3.5
Classifier: Programming Language :: Python :: 3.6
